Workbook

Sheet Dashboard
A1: DASHBOARD - AI MATURITY ASSESSMENT
B3: PUNTEGGIO COMPLESSIVO (0-100) | F3: LEGENDA LIVELLI DI MATURITÀ
B4: =Calcoli!I30 -> 40.6 | F4: 0-20 | G4: Iniziale
B5: LIVELLO | F5: 21-40 | G5: Consapevole
B6: =Calcoli!G32 -> In Sviluppo | F6: 41-60 | G6: In Sviluppo
F7: 61-80 | G7: Avanzato
F8: 81-100 | G8: Leader
B9: PUNTEGGI PER AREA
B10: Area | C10: Punteggio | D10: Peso | E10: Contributo
B11: =Calcoli!F23 -> 1. Governance e Strategia | C11: =Calcoli!H23 -> 36.666667 | D11: =Calcoli!I23 -> 0.25 | E11: =Calcoli!J23 -> 9.1666667
B12: =Calcoli!F24 -> 2. Cultura e Change Management | C12: =Calcoli!H24 -> 50 | D12: =Calcoli!I24 -> 0.25 | E12: =Calcoli!J24 -> 12.5
B13: =Calcoli!F25 -> 3. Maturità Digitale Dipendenti | C13: =Calcoli!H25 -> 26.666667 | D13: =Calcoli!I25 -> 0.16 | E13: =Calcoli!J25 -> 4.2666667
B14: =Calcoli!F26 -> 4. Infrastruttura e Dati | C14: =Calcoli!H26 -> 46.666667 | D14: =Calcoli!I26 -> 0.22 | E14: =Calcoli!J26 -> 10.266667
B15: =Calcoli!F27 -> 5. Innovazione e Ricerca | C15: =Calcoli!H27 -> 36.666667 | D15: =Calcoli!I27 -> 0.12 | E15: =Calcoli!J27 -> 4.4
B18: ANALISI GAP E RACCOMANDAZIONI
B19: Aree con punteggio < 40 (CRITICHE)
B20: Aree con punteggio 40-70 (ATTENZIONE)
B21: Aree con punteggio > 70 (PUNTI DI FORZA)
B24: NOTE INTERPRETATIVE (SCALA 0-5 CORRETTA)
B25: • Scala 0-5: Il punteggio minimo è 0 (assente) e massimo è 100 (eccellenza), sfruttando l'intero range.
B26: • Un punteggio basso identifica precisamente le aree critiche su cui investire prioritariamente.
B27: • Le aree "Governance" e "Infrastruttura" pesano 25% ciascuna: sono fondamentali e bloccanti.
B28: • È normale avere disomogeneità: concentrarsi prima sulle criticità con peso maggiore.
B29: • Ripetere l'assessment ogni 6-12 mesi per monitorare progressi e ROI degli investimenti.

Sheet Questionario
A1: AI MATURITY ASSESSMENT - QUESTIONARIO
A3: ISTRUZIONI: Per ogni domanda, selezionare il livello che meglio descrive la situazione attuale (0=Assente, 5=Ottimale). Scala 0-5 per sfruttare l'intero range di valutazione.
A5: Area | B5: Codice | C5: Domanda | D5: Risposta (0-5) | E5: Descrizione Livello | F5: Note
A6: GOVERNANCE E STRATEGIA | B6: 1.1.a | C6: In quale fase si trova attualmente l'organizzazione rispetto alla definizione di una roadmap per l'intelligenza artificiale? | D6: 1 | E6: 0=Inesistente | 1=Mai discussa formalmente | 2=In discussione iniziale | 3=Abbozzata | 4=Documentata e condivisa | 5=Formalizzata e in implementazione
B7: 1.1.b | C7: Come vengono identificate e prioritizzate le opportunità di applicazione dell'IA? | D7: 2 | E7: 0=Nessun processo | 1=Approccio casuale | 2=Su richiesta dipartimenti | 3=Iniziative sporadiche | 4=Processo definito | 5=Metodologia strutturata ricorrente
B9: 1.2.a | C9: Chi si occupa attualmente di valutare e proporre soluzioni basate su intelligenza artificiale? | D9: 1 | E9: 0=Nessuno | 1=Interesse occasionale | 2=Risorse IT generiche | 3=Individui senza mandato | 4=Gruppo informale | 5=Team dedicato con budget
B10: 1.2.b | C10: Quale livello di autonomia decisionale ha chi si occupa di iniziative AI? | D10: 4 | E10: 0=Non applicabile | 1=Nessuna autonomia | 2=Molteplici approvazioni | 3=Limitata per piloti | 4=Media entità | 5=Piena autonomia strategica
B12: 1.3.a | C12: In che modo le iniziative tecnologiche emergenti vengono valutate rispetto agli obiettivi di business? | D12: 2 | E12: 0=Nessuna valutazione | 1=Nessuna connessione | 2=Caso per caso | 3=Framework generale | 4=Mappate su obiettivi | 5=Integrate in pianificazione
B13: 1.3.b | C13: Con quale frequenza il management discute l'impatto potenziale delle nuove tecnologie? | D13: 1 | E13: 0=Mai | 1=Molto raramente | 2=Opportunità specifiche | 3=Annuale | 4=Trimestrale | 5=Permanente in direzione
A16: CULTURA AZIENDALE E CHANGE MANAGEMENT | B16: 2.1.a | C16: Quando vengono menzionate nuove tecnologie come l'IA, qual è la reazione prevalente dei dipendenti? | D16: 3 | E16: 0=Ostilità | 1=Forte resistenza | 2=Indifferenza | 3=Curiosità superficiale | 4=Interesse attivo | 5=Entusiasmo e proposte
B17: 2.1.b | C17: In quale percentuale i dipendenti hanno avuto esperienza diretta con strumenti basati su AI? | D17: 4 | E17: 0=0% | 1=<10% | 2=10-30% | 3=30-50% | 4=50-70% | 5=>70%
B19: 2.2.a | C19: Come vengono gestiti tipicamente i cambiamenti significativi nei processi o negli strumenti? | D19: 5 | E19: 0=Nessuna gestione | 1=Imposizione senza supporto | 2=Comunicazione post | 3=Comunicazione pre | 4=Con formazione base | 5=Gestione completa strutturata
B20: 2.2.b | C20: Quale supporto ricevono i dipendenti durante l'introduzione di nuovi strumenti tecnologici? | D20: 0 | E20: 0=Nessun supporto | 1=Supporto minimo | 2=Documentazione | 3=Sessione formativa | 4=Formazione+helpdesk | 5=Piano accompagnamento completo
B22: 2.3.a | C22: Negli ultimi 12 mesi, quante ore di formazione digitale ha ricevuto in media ciascun dipendente? | D22: 2 | E22: 0=Nessuna | 1=<2 ore | 2=2-5 ore | 3=5-15 ore | 4=15-30 ore | 5=>30 ore
B23: 2.3.b | C23: Quale approccio viene utilizzato per lo sviluppo delle competenze digitali? | D23: 1 | E23: 0=Nessun approccio | 1=Informale sporadico | 2=Occasionale | 3=Catalogo on demand | 4=Piano per ruoli | 5=Percorsi personalizzati con assessment
A26: MATURITÀ DIGITALE DEI DIPENDENTI | B26: 3.1.a | C26: Qual è il livello di autonomia dei dipendenti nell'utilizzo di strumenti digitali complessi? | D26: 1 | E26: 0=Non utilizzano digitale | 1=Difficoltà base | 2=Solo familiari | 3=Standard con supporto | 4=Apprendimento autonomo | 5=Pienamente autonomi
B27: 3.1.b | C27: Come reagiscono i dipendenti quando devono apprendere nuove funzionalità software? | D27: 2 | E27: 0=Rifiuto | 1=Forte resistenza | 2=Accettazione passiva | 3=Adattamento guidato | 4=Proattività | 5=Entusiasmo e sperimentazione
B29: 3.2.a | C29: Con quale frequenza i dipendenti propongono spontaneamente l'adozione di nuovi strumenti digitali? | D29: 0 | E29: 0=Mai | 1=Molto raramente | 2=Raramente (annuale) | 3=Occasionalmente (trimestrale) | 4=Regolarmente (mensile) | 5=Frequentemente (bottom-up)
B30: 3.2.b | C30: Qual è il tempo medio necessario perché un nuovo strumento raggiunga utilizzo diffuso (>70%)? | D30: 3 | E30: 0=Mai raggiunto | 1=>12 mesi | 2=6-12 mesi | 3=3-6 mesi | 4=1-3 mesi | 5=<1 mese
B32: 3.3.a | C32: Quando si parla di automazione e IA, quali sono le preoccupazioni più frequenti? | D32: 0 | E32: 0=Paura paralizzante | 1=Timore perdita lavoro | 2=Dubbi capacità gestione | 3=Qualità/affidabilità | 4=Interesse etico | 5=Curiosità integrazione
B33: 3.3.b | C33: Come viene percepita la trasparenza dell'organizzazione sull'uso di tecnologie avanzate? | D33: 2 | E33: 0=Opacità totale | 1=Assente | 2=Minima reattiva | 3=Occasionale | 4=Regolare proattiva | 5=Coinvolgimento attivo decisioni
A36: INFRASTRUTTURA TECNOLOGICA E DATI | B36: 4.1.a | C36: Quale percentuale dei sistemi aziendali è stata aggiornata negli ultimi 3 anni? | D36: 1 | E36: 0=0% | 1=<20% | 2=20-40% | 3=40-60% | 4=60-80% | 5=>80%
B37: 4.1.b | C37: Come viene gestita l'infrastruttura IT in relazione a nuove esigenze computazionali? | D37: 2 | E37: 0=Inesistente/obsoleta | 1=Rigida | 2=Lenta (>6m) | 3=Media (3-6m) | 4=Flessibile (1-3m) | 5=Cloud dinamica immediata
B39: 4.2.a | C39: Quanto tempo è necessario per estrarre e aggregare dati da diverse fonti per un'analisi? | D39: 4 | E39: 0=Impossibile | 1=>1 settimana | 2=3-7 giorni | 3=1-3 giorni | 4=Poche ore | 5=Minuti (self-service)
B40: 4.2.b | C40: In quale formato sono prevalentemente conservati i dati aziendali critici? | D40: 2 | E40: 0=Non digitalizzati | 1=Cartaceo/file | 2=Legacy isolati | 3=DB limitata integrazione | 4=Data warehouse | 5=Data lake moderno
B42: 4.3.a | C42: Esistono policy documentate per la gestione del ciclo di vita dei dati? | D42: 5 | E42: 0=Non esistono | 1=Solo verbali | 2=Informali | 3=Documentate non applicate | 4=Applicate periodicamente | 5=Framework completo
B43: 4.3.b | C43: Come viene garantita la conformità alle normative sulla protezione dei dati (es. GDPR)? | D43: 0 | E43: 0=Non conformi | 1=Non verificata | 2=Reattiva | 3=Verifica annuale | 4=Audit periodici | 5=Privacy by design + DPO
A46: CAPACITÀ DI INNOVAZIONE E RICERCA | B46: 5.1.a | C46: Quale percentuale del fatturato viene destinata a ricerca, sviluppo e innovazione? | D46: 2 | E46: 0=0% | 1=<0.5% | 2=0.5-1% | 3=1-3% | 4=3-5% | 5=>5%
B47: 5.1.b | C47: Come vengono allocate le risorse per progetti innovativi? | D47: 3 | E47: 0=Nessun budget | 1=Sporadico ad-hoc | 2=Residuale | 3=Budget fisso | 4=Con revisione periodica | 5=Innovation fund strutturato
B49: 5.2.a | C49: Quante partnership attive con università/centri di ricerca/startup ha l'organizzazione? | D49: 1 | E49: 0=Nessuna | 1=1 sporadica | 2=1-2 occasionali | 3=3-5 | 4=6-10 strutturate | 5=>10 con framework
B50: 5.2.b | C50: In che modo l'organizzazione si tiene aggiornata sulle innovazioni del settore? | D50: 2 | E50: 0=Non monitora | 1=Nessun processo | 2=Occasionale | 3=Monitoraggio passivo | 4=Partecipazione regolare | 5=Ecosystem attivo
B52: 5.3.a | C52: Negli ultimi 24 mesi, quanti progetti pilota su tecnologie emergenti sono stati avviati? | D52: 1 | E52: 0=Nessuno | 1=1 tentativo | 2=1-2 | 3=3-5 | 4=6-10 | 5=>10 con metodologia
B53: 5.3.b | C53: Qual è il tasso di successo (pilota→produzione) dei progetti innovativi? | D53: 2 | E53: 0=0% o N/A | 1=<10% | 2=10-25% | 3=25-40% | 4=40-60% | 5=>60% con processo

Sheet Calcoli
A1: CALCOLI PUNTEGGI - AI MATURITY ASSESSMENT (Scala 0-5)
A3: SISTEMA DI PESATURA | F3: CALCOLO PUNTEGGI PER ELEMENTO (Scala 0-5)
A4: Area | B4: Peso Area | C4: Elemento | D4: Peso Elemento | F4: Elemento | G4: Domanda A | H4: Domanda B | I4: Media (0-5) | J4: Punteggio %
A5: 1. Governance e Strategia | B5: =I23 -> 0.25 | C5: 1.1 | D5: 0.3333 | F5: 1.1 | G5: =Questionario!D6 -> 1 | H5: =Questionario!D7 -> 2 | I5: =(G5+H5)/2 -> 1.5 | J5: =I5/5*100 -> 30
C6: 1.2 | D6: 0.3333 | F6: 1.2 | G6: =Questionario!D9 -> 1 | H6: =Questionario!D10 -> 4 | I6: =(G6+H6)/2 -> 2.5 | J6: =I6/5*100 -> 50
C7: 1.3 | D7: 0.3333 | F7: 1.3 | G7: =Questionario!D12 -> 2 | H7: =Questionario!D13 -> 1 | I7: =(G7+H7)/2 -> 1.5 | J7: =I7/5*100 -> 30
A8: 2. Cultura e Change Management | B8: =I24 -> 0.25 | C8: 2.1 | D8: 0.3333 | F8: 2.1 | G8: =Questionario!D16 -> 3 | H8: =Questionario!D17 -> 4 | I8: =(G8+H8)/2 -> 3.5 | J8: =I8/5*100 -> 70
C9: 2.2 | D9: 0.3333 | F9: 2.2 | G9: =Questionario!D19 -> 5 | H9: =Questionario!D20 -> 0 | I9: =(G9+H9)/2 -> 2.5 | J9: =I9/5*100 -> 50
C10: 2.3 | D10: 0.3333 | F10: 2.3 | G10: =Questionario!D22 -> 2 | H10: =Questionario!D23 -> 1 | I10: =(G10+H10)/2 -> 1.5 | J10: =I10/5*100 -> 30
A11: 3. Maturità Digitale Dipendenti | B11: =I25 -> 0.16 | C11: 3.1 | D11: 0.3333 | F11: 3.1 | G11: =Questionario!D26 -> 1 | H11: =Questionario!D27 -> 2 | I11: =(G11+H11)/2 -> 1.5 | J11: =I11/5*100 -> 30
C12: 3.2 | D12: 0.3333 | F12: 3.2 | G12: =Questionario!D29 -> 0 | H12: =Questionario!D30 -> 3 | I12: =(G12+H12)/2 -> 1.5 | J12: =I12/5*100 -> 30
C13: 3.3 | D13: 0.3333 | F13: 3.3 | G13: =Questionario!D32 -> 0 | H13: =Questionario!D33 -> 2 | I13: =(G13+H13)/2 -> 1 | J13: =I13/5*100 -> 20
A14: 4. Infrastruttura e Dati | B14: =I26 -> 0.22 | C14: 4.1 | D14: 0.3333 | F14: 4.1 | G14: =Questionario!D36 -> 1 | H14: =Questionario!D37 -> 2 | I14: =(G14+H14)/2 -> 1.5 | J14: =I14/5*100 -> 30
C15: 4.2 | D15: 0.3333 | F15: 4.2 | G15: =Questionario!D39 -> 4 | H15: =Questionario!D40 -> 2 | I15: =(G15+H15)/2 -> 3 | J15: =I15/5*100 -> 60
C16: 4.3 | D16: 0.3333 | F16: 4.3 | G16: =Questionario!D42 -> 5 | H16: =Questionario!D43 -> 0 | I16: =(G16+H16)/2 -> 2.5 | J16: =I16/5*100 -> 50
A17: 5. Innovazione e Ricerca | B17: =I27 -> 0.12 | C17: 5.1 | D17: 0.3333 | F17: 5.1 | G17: =Questionario!D46 -> 2 | H17: =Questionario!D47 -> 3 | I17: =(G17+H17)/2 -> 2.5 | J17: =I17/5*100 -> 50
C18: 5.2 | D18: 0.3333 | F18: 5.2 | G18: =Questionario!D49 -> 1 | H18: =Questionario!D50 -> 2 | I18: =(G18+H18)/2 -> 1.5 | J18: =I18/5*100 -> 30
C19: 5.3 | D19: 0.3333 | F19: 5.3 | G19: =Questionario!D52 -> 1 | H19: =Questionario!D53 -> 2 | I19: =(G19+H19)/2 -> 1.5 | J19: =I19/5*100 -> 30
F21: PUNTEGGI PER AREA
F22: Area | G22: Elementi | H22: Media Area | I22: Peso | J22: Punteggio Pesato
F23: 1. Governance e Strategia | G23: x.1-x.3 | H23: =AVERAGE(J5:J7) -> 36.666667 | I23: 0.25 | J23: =H23*I23 -> 9.1666667
F24: 2. Cultura e Change Management | G24: x.1-x.3 | H24: =AVERAGE(J8:J10) -> 50 | I24: 0.25 | J24: =H24*I24 -> 12.5
F25: 3. Maturità Digitale Dipendenti | G25: x.1-x.3 | H25: =AVERAGE(J11:J13) -> 26.666667 | I25: 0.16 | J25: =H25*I25 -> 4.2666667
F26: 4. Infrastruttura e Dati | G26: x.1-x.3 | H26: =AVERAGE(J14:J16) -> 46.666667 | I26: 0.22 | J26: =H26*I26 -> 10.266667
F27: 5. Innovazione e Ricerca | G27: x.1-x.3 | H27: =AVERAGE(J17:J19) -> 36.666667 | I27: 0.12 | J27: =H27*I27 -> 4.4
F30: PUNTEGGIO TOTALE AI MATURITY (0-100) | I30: =SUM(J23:J27) -> 40.6
F32: LIVELLO DI MATURITÀ | G32: =IF(I30<=20,"Iniziale",IF(I30<=40,"Consapevole",IF(I30<=60,"In Sviluppo",IF(I30<=80,"Avanzato","Leader")))) -> In Sviluppo
A35: Area | B35: Punteggio | C35: MAX
A36: 1. Governance e Strategia | B36: =J23 -> 9.1666667 | C36: =I23*100 -> 25
A37: 2. Cultura e Change Management | B37: =J24 -> 12.5 | C37: =I24*100 -> 25
A38: 3. Maturità Digitale Dipendenti | B38: =J25 -> 4.2666667 | C38: =I25*100 -> 16
A39: 4. Infrastruttura e Dati | B39: =J26 -> 10.266667 | C39: =I26*100 -> 22
A40: 5. Innovazione e Ricerca | B40: =J27 -> 4.4 | C40: =I27*100 -> 12

Sheet Domande
A4: AREA 1: GOVERNANCE E STRATEGIA | B4: VAL.
A5: Elemento 1.1: Strategia AI definita
A6: 1.1.a In quale fase si trova attualmente l'organizzazione rispetto alla definizione di una roadmap per l'intelligenza artificiale? • 0 = Inesistente, nessuna discussione o considerazione in merito • 1 = Mai discussa formalmente in nessuna sede • 2 = È in fase di discussione iniziale • 3 = È stata abbozzata ma non formalizzata • 4 = È documentata e condivisa con stakeholder • 5 = È formalizzata, comunicata e in fase di implementazione attiva
A7: 1.1.b Come vengono identificate e prioritizzate le opportunità di applicazione dell'IA all'interno dell'organizzazione? • 0 = Nessun processo, nessuna considerazione • 1 = Approccio casuale • 2 = Su richiesta spontanea dei singoli • 3 = Attraverso iniziative sporadiche del management • 4 = Con un processo definito ma non sistematico • 5 = Con metodologia strutturata e ricorrente di scouting e valutazione
A8: Elemento 1.2: Team o responsabile AI
A9: 1.2.a Chi si occupa attualmente di valutare e proporre soluzioni basate su intelligenza artificiale? • 0 = Nessuna considerazione del tema • 1 = Interesse occasionale senza responsabilità specifiche • 2 = Risorse IT che si occupano anche di altro • 3 = Singoli individui interessati senza mandato formale • 4 = Un gruppo informale cross-funzionale • 5 = Un team dedicato o responsabile con budget e mandato esplicito
A10: 1.2.b Quale livello di autonomia decisionale ha chi si occupa di iniziative AI nell'allocazione di risorse? • 0 = Non applicabile (nessuno si occupa di AI) • 1 = Nessuna autonomia • 2 = Deve passare attraverso molteplici livelli di approvazione • 3 = Ha autonomia limitata per progetti pilota • 4 = Ha autonomia per progetti di media entità • 5 = Ha piena autonomia strategica e budget dedicato
A11: Elemento 1.3: Allineamento strategico
A12: 1.3.a In che modo le iniziative tecnologiche emergenti vengono valutate rispetto agli obiettivi di business? • 0 = Nessuna valutazione rispetto agli obiettivi • 1 = Non esiste una connessione esplicita tra iniziative e obiettivi • 2 = Vengono valutate caso per caso senza criteri uniformi • 3 = Esiste un framework generale per l'innovazione tecnologica • 4 = Vengono mappate su obiettivi specifici di business • 5 = Sono parte integrante della pianificazione strategica annuale
A13: 1.3.b Con quale frequenza il management discute e valuta l'impatto potenziale ed effettivo delle nuove tecnologie sui risultati aziendali? • 0 = Mai • 1 = Molto raramente (mino di una volta all'anno) • 2 = Solo quando si presentano opportunità specifiche • 3 = In occasione della pianificazione annuale • 4 = Trimestralmente in review strutturate • 5 = È un tema che fa parte dell'agenda delle riunioni di direzione
A14: AREA 2: CULTURA AZIENDALE E CHANGE MANAGEMENT
A15: Elemento 2.1: Conoscenza e accettazione dell'AI
A16: 2.1.a Quando vengono menzionate nuove tecnologie come l'intelligenza artificiale, qual è la reazione prevalente dei dipendenti? • 0 = Ostilità aperta e blocco • 1 = Forte scetticismo e resistenza • 2 = Indifferenza o disinteresse • 3 = Curiosità superficiale • 4 = Interesse attivo con richieste di approfondimento • 5 = Entusiasmo e proposta spontanea di casi d'uso
... A53: 5.3.b Qual è il tasso di successo (passaggio da pilota a produzione) dei progetti innovativi? • 0 = 0% o non applicabile (nessun progetto) • 1 = Meno del 20% • 2 = Tra 20% e 40% • 3 = Tra 40% e 60% • 4 = Tra 60% e 80% • 5 = Oltre 80% con processo di scaling definito
